feature_engineering/__init__.py
feature_engineering/drop_columns.py
feature_engineering/fill_na_values.py
feature_engineering/one_hot_encoding.py
one_hot_encoding/__init__.py
s3_interface/__init__.py
s3_interface/download_file.py
kaagle_library_bharadwaj-0.0.8.dist-info/LICENSE
kaagle_library_bharadwaj-0.0.8.dist-info/METADATA
kaagle_library_bharadwaj-0.0.8.dist-info/WHEEL
kaagle_library_bharadwaj-0.0.8.dist-info/top_level.txt
kaagle_library_bharadwaj-0.0.8.dist-info/RECORD
